pjeuler/__init__.py
pjeuler/pjeuler.py
pjeuler/pjeuler1.py
pjeuler/tools.py
pjeuler_chicotobi-0.8.0.dist-info/LICENSE
pjeuler_chicotobi-0.8.0.dist-info/METADATA
pjeuler_chicotobi-0.8.0.dist-info/WHEEL
pjeuler_chicotobi-0.8.0.dist-info/top_level.txt
pjeuler_chicotobi-0.8.0.dist-info/RECORD
